eLearning/__init__.py
eLearning/connector.py
eLearning/test.py
eLearning/users.py
eLearning-0.0.5.dist-info/LICENSE
eLearning-0.0.5.dist-info/METADATA
eLearning-0.0.5.dist-info/WHEEL
eLearning-0.0.5.dist-info/top_level.txt
eLearning-0.0.5.dist-info/RECORD
