Metadata-Version: 2.1
Name: eLearning
Version: 0.0.5
Summary: eLearning is an API dedicated to managing the backend infrastructure of an e-learning system.
Home-page: https://github.com/Ivanfdezr/DACODES-CHALLENGE
Author: Ivan Y. Fernandez-Rosales
Author-email: ifdezr@gmail.com
License: UNKNOWN
Platform: UNKNOWN
Classifier: Programming Language :: Python :: 3
Classifier: License :: OSI Approved :: GNU General Public License v3 (GPLv3)
Classifier: Operating System :: Microsoft :: Windows :: Windows 10
Requires-Python: >=3.6
